setup.py
bloomzip/__init__.py
bloomzip/bloomzip.py
bloomzip.egg-info/PKG-INFO
bloomzip.egg-info/SOURCES.txt
bloomzip.egg-info/dependency_links.txt
bloomzip.egg-info/not-zip-safe
bloomzip.egg-info/top_level.txt
test/test_bloomzip.py