Metadata-Version: 1.0
Name: bloomzip
Version: 0.1
Summary: A module for creating compressed files with a precursory bloom filter
Home-page: https://github.com/stiege/bloomzip
Author: Alex Hodge
Author-email: alex.hodge.nz@gmail.com
License: MIT
Platform: UNKNOWN
